[
    {
      "name": "John Doe",
      "email": "john.doe@example.com",
      "contact": "+1234567890",
      "aadhaar": "123456789012",
      "current_address": "123 Main St, City, Country",
      "permanent_address": "456 Oak Ave, Town, Country",
      "license": "1234"
    },
    {
      "name": "Jane Smith",
      "email": "jane.smith@example.com",
      "contact": "+9876543210",
      "aadhaar": "987654321098",
      "current_address": "789 Elm St, City, Country",
      "permanent_address": "321 Maple Ave, Town, Country",
      "license": "5678"
    },
    {
      "name": "Alice Johnson",
      "email": "alice.johnson@example.com",
      "contact": "+1122334455",
      "aadhaar": "111122223333",
      "current_address": "456 Pine St, City, Country",
      "permanent_address": "789 Cedar Ave, Town, Country",
      "license": "9012"
    },
    {
      "name": "Bob Williams",
      "email": "bob.williams@example.com",
      "contact": "+9988776655",
      "aadhaar": "444433332222",
      "current_address": "987 Oak St, City, Country",
      "permanent_address": "654 Birch Ave, Town, Country",
      "license": "3456"
    },
    {
      "name": "Emily Brown",
      "email": "emily.brown@example.com",
      "contact": "+3344556677",
      "aadhaar": "555566667777",
      "current_address": "321 Elm St, City, Country",
      "permanent_address": "876 Cedar Ave, Town, Country",
      "license": "7890"
    },
    {
      "name": "Michael Garcia",
      "email": "michael.garcia@example.com",
      "contact": "+1122334455",
      "aadhaar": "888899997777",
      "current_address": "654 Oak St, City, Country",
      "permanent_address": "123 Pine Ave, Town, Country",
      "license": "2345"
    },
    {
      "name": "Sophia Martinez",
      "email": "sophia.martinez@example.com",
      "contact": "+9988776655",
      "aadhaar": "333344445555",
      "current_address": "876 Maple St, City, Country",
      "permanent_address": "987 Cedar Ave, Town, Country",
      "license": "6789"
    },
    {
      "name": "William Lee",
      "email": "william.lee@example.com",
      "contact": "+3344556677",
      "aadhaar": "999988887777",
      "current_address": "123 Pine St, City, Country",
      "permanent_address": "456 Elm Ave, Town, Country",
      "license": "4321"
    },
    {
      "name": "Olivia Rodriguez",
      "email": "olivia.rodriguez@example.com",
      "contact": "+1122334455",
      "aadhaar": "666677778888",
      "current_address": "789 Cedar St, City, Country",
      "permanent_address": "321 Oak Ave, Town, Country",
      "license": "9876"
    },
    {
      "name": "Liam Smith",
      "email": "liam.smith@example.com",
      "contact": "+9988776655",
      "aadhaar": "111100002222",
      "current_address": "987 Birch St, City, Country",
      "permanent_address": "654 Pine Ave, Town, Country",
      "license": "5432"
    },
    {
      "name": "Ava Hernandez",
      "email": "ava.hernandez@example.com",
      "contact": "+3344556677",
      "aadhaar": "777766665555",
      "current_address": "654 Maple St, City, Country",
      "permanent_address": "123 Cedar Ave, Town, Country",
      "license": "2109"
    },
    {
      "name": "Noah Gonzalez",
      "email": "noah.gonzalez@example.com",
      "contact": "+1122334455",
      "aadhaar": "333322221111",
      "current_address": "123 Elm St, City, Country",
      "permanent_address": "456 Oak Ave, Town, Country",
      "license": "8765"
    },
    {
      "name": "Isabella Wilson",
      "email": "isabella.wilson@example.com",
      "contact": "+9988776655",
      "aadhaar": "666655554444",
      "current_address": "789 Pine St, City, Country",
      "permanent_address": "321 Maple Ave, Town, Country",
      "license": "1098"
    },
    {
      "name": "James Anderson",
      "email": "james.anderson@example.com",
      "contact": "+3344556677",
      "aadhaar": "888899991111",
      "current_address": "987 Cedar St, City, Country",
      "permanent_address": "654 Oak Ave, Town, Country",
      "license": "6543"
    },
    {
      "name": "Charlotte Taylor",
      "email": "charlotte.taylor@example.com",
      "contact": "+1122334455",
      "aadhaar": "444455556666",
      "current_address": "654 Pine St, City, Country",
      "permanent_address": "123 Birch Ave, Town, Country",
      "license": "2109"
    },
    {
      "name": "Benjamin Thomas",
      "email": "benjamin.thomas@example.com",
      "contact": "+9988776655",
      "aadhaar": "777766665555",
      "current_address": "789 Cedar St, City, Country",
      "permanent_address": "321 Elm Ave, Town, Country",
      "license": "8765"
    },
    {
      "name": "Amelia Moore",
      "email": "amelia.moore@example.com",
      "contact": "+3344556677",
      "aadhaar": "222233334444",
      "current_address": "987 Maple St, City, Country",
      "permanent_address": "654 Pine Ave, Town, Country",
      "license": "5432"
    },
    {
      "name": "Ethan Jackson",
      "email": "ethan.jackson@example.com",
      "contact": "+1122334455",
      "aadhaar": "999988887777",
      "current_address": "123 Cedar St, City, Country",
      "permanent_address": "456 Oak Ave, Town, Country",
      "license": "2109"
    },
    {
      "name": "Mia White",
      "email": "mia.white@example.com",
      "contact": "+9988776655",
      "aadhaar": "666655554444",
      "current_address": "789 Pine St, City, Country",
      "permanent_address": "321 Maple Ave, Town, Country",
      "license": "8765"
    },
    {
      "name": "Alexander Harris",
      "email": "alexander.harris@example.com",
      "contact": "+3344556677",
      "aadhaar": "888899991111",
      "current_address": "987 Cedar St, City, Country",
      "permanent_address": "654 Oak Ave, Town, Country",
      "license": "5432"
    }
  ]
  